conehull/__init__.py
conehull/_cone_intersection.py
conehull/_conehull.py
conehull/_geometry.py
conehull/sampler.py
conehull/view.py
conehull-1.0.1.dist-info/METADATA
conehull-1.0.1.dist-info/WHEEL
conehull-1.0.1.dist-info/licenses/LICENSE
conehull-1.0.1.dist-info/RECORD
