Metadata-Version: 2.4
Name: conehull
Version: 1.0.1
Summary: 2D convex hull algorithm with directional cone constraints and visualization tools.
Project-URL: Homepage, https://github.com/Kalmander/conehull
Project-URL: Issues, https://github.com/Kalmander/conehull/issues
Author-email: Tryggvi Kalman Jónsson <tryggvikalman@proton.me>
License-Expression: GPL-3.0-or-later
License-File: LICENSE
Keywords: computational geometry,cone constraints,convex hull,quickhull,visualization
Classifier: Operating System :: OS Independent
Classifier: Programming Language :: Python :: 3
Requires-Python: >=3.9
Requires-Dist: matplotlib>=3.3.0
Requires-Dist: numpy>=1.18.0
Requires-Dist: scikit-image>=0.18.0
Requires-Dist: scipy>=1.6.0
